CHANGES
LICENSE
MANIFEST.in
README.md
setup.py
src/main/python/scrum_tools.egg-info/PKG-INFO
src/main/python/scrum_tools.egg-info/SOURCES.txt
src/main/python/scrum_tools.egg-info/dependency_links.txt
src/main/python/scrum_tools.egg-info/requires.txt
src/main/python/scrum_tools.egg-info/top_level.txt
src/main/python/scrumtools/__init__.py
src/main/python/scrumtools/base.py
src/main/python/scrumtools/data.py
src/main/python/scrumtools/error.py
src/main/python/scrumtools/github.py
src/main/python/scrumtools/trello.py
src/main/scripts/scrum-tools