Metadata-Version: 1.1
Name: scrum-tools
Version: 0.1.0
Summary: A set of CLI tools for batch management of Scrum infrastructure (GitHub, Trello).
Home-page: https://github.com/TU-Berlin-DIMA/scrum-tools
Author: Alexander Alexandrov
Author-email: alexander.alexandrov@tu-berlin.de
License: Apache v2 Licence, see LICENCE file
Platform: UNKNOWN
Classifier: Development Status :: 3 - Alpha
Classifier: Environment :: Console
Classifier: Framework :: Django
Classifier: Intended Audience :: Developers
Classifier: License :: OSI Approved :: Apache Software License
Classifier: Natural Language :: English
Classifier: Programming Language :: Python
Classifier: Topic :: Software Development
